smawe_tools/__init__.py
smawe_tools/__version__.py
smawe_tools/algorithm.py
smawe_tools/config.py
smawe_tools/settings.py
smawe_tools/tool.py
smawe_tools/utils.py
smawe_tools/exception/__init__.py
smawe_tools/net/__init__.py
smawe_tools/net/network_tool.py
smawe_tools/retrying/__init__.py
smawe_tools/retrying/retry.py
smawe_tools/struct/__init__.py
smawe_tools-0.4.2.dist-info/LICENSE
smawe_tools-0.4.2.dist-info/METADATA
smawe_tools-0.4.2.dist-info/WHEEL
smawe_tools-0.4.2.dist-info/top_level.txt
smawe_tools-0.4.2.dist-info/RECORD
